fallpwn/__init__.py
fallpwn/gadgets/__init__.py
fallpwn/gadgets/get_gadgets.py
fallpwn/rop/__init__.py
fallpwn/rop/get_gadgets.py
fallpwn/rop/rop_payload.py
fallpwn-0.1.3.dist-info/LICENSE
fallpwn-0.1.3.dist-info/METADATA
fallpwn-0.1.3.dist-info/WHEEL
fallpwn-0.1.3.dist-info/top_level.txt
fallpwn-0.1.3.dist-info/RECORD
